datalite/__init__.py
datalite/commons.py
datalite/constraints.py
datalite/datalite_decorator.py
datalite/fetch.py
datalite/mass_actions.py
datalite/migrations.py
test/__init__.py
test/main_tests.py
datalite-0.7.3.dist-info/LICENSE
datalite-0.7.3.dist-info/METADATA
datalite-0.7.3.dist-info/WHEEL
datalite-0.7.3.dist-info/top_level.txt
datalite-0.7.3.dist-info/RECORD
