Metadata-Version: 2.1
Name: datalite
Version: 0.7.3
Summary: A small package that binds dataclasses to an sqlite database
Home-page: https://github.com/ambertide/datalite
Author: Ege Ozkan
Author-email: egeemirozkan24@gmail.com
License: UNKNOWN
Platform: UNKNOWN
Classifier: Programming Language :: Python :: 3.7
Classifier: License :: OSI Approved :: MIT License
Classifier: Operating System :: OS Independent
Requires-Python: >=3.7
